setup.py
utfhate/__init__.py
utfhate/utfhate.py
utfhate.egg-info/PKG-INFO
utfhate.egg-info/SOURCES.txt
utfhate.egg-info/dependency_links.txt
utfhate.egg-info/requires.txt
utfhate.egg-info/top_level.txt