Metadata-Version: 1.0
Name: utfhate
Version: 1.0.6
Summary: Doing BAD THINGSTM to UTF-8 byte strings and unicode strings
Home-page: https://github.com/kmyr/utfhate
Author: Mikael Kohlmyr
Author-email: mikael@kohlmyr.com
License: LICENSE
Platform: UNKNOWN
